falcon_multipart/parser.py
falcon_multipart/middleware.py
falcon_multipart/__init__.py
falcon_multipart-0.2.0.dist-info/metadata.json
falcon_multipart-0.2.0.dist-info/METADATA
falcon_multipart-0.2.0.dist-info/RECORD
falcon_multipart-0.2.0.dist-info/WHEEL
falcon_multipart-0.2.0.dist-info/top_level.txt
falcon_multipart-0.2.0.dist-info/DESCRIPTION.rst
